adam/__init__.py
adam/app.py
adam/mpbc/__init__.py
adam/mpbc/__init__.py~
adam/mpbc/info.py
adam/mpbc/info.py~
adam/mpbc/__pycache__/info.cpython-35.pyc
adam/static/favicon.ico
adam/static/img/logo.png
adam/static/img/ports.png
adam/static/img/touch_screen.png
adam/static/img/usb.png
adam/static/styles/css/bootstrap-theme.css
adam/static/styles/css/bootstrap-theme.css.map
adam/static/styles/css/bootstrap-theme.min.css
adam/static/styles/css/bootstrap-theme.min.css.map
adam/static/styles/css/bootstrap.css
adam/static/styles/css/bootstrap.css.map
adam/static/styles/css/bootstrap.min.css
adam/static/styles/css/bootstrap.min.css.map
adam/static/styles/css/bundled.css
adam/static/styles/css/font-awesome.min.css
adam/static/styles/css/fontawesome-all.css
adam/static/styles/css/jquery-confirm.min.css
adam/static/styles/css/keyboard.css
adam/static/styles/css/select2.min.css
adam/static/styles/css/style.css
adam/static/styles/css/style.css~
adam/static/styles/fonts/FontAwesome.otf
adam/static/styles/fonts/fontawesome-webfont.eot
adam/static/styles/fonts/fontawesome-webfont.svg
adam/static/styles/fonts/fontawesome-webfont.ttf
adam/static/styles/fonts/fontawesome-webfont.woff
adam/static/styles/fonts/fontawesome-webfont.woff2
adam/static/styles/fonts/glyphicons-halflings-regular.eot
adam/static/styles/fonts/glyphicons-halflings-regular.svg
adam/static/styles/fonts/glyphicons-halflings-regular.ttf
adam/static/styles/fonts/glyphicons-halflings-regular.woff
adam/static/styles/fonts/glyphicons-halflings-regular.woff2
adam/static/styles/images/bg-track.png
adam/static/styles/images/handle.png
adam/static/styles/images/volume.png
adam/static/styles/js/bootstrap.js
adam/static/styles/js/bootstrap.min.js
adam/static/styles/js/bundled.js
adam/static/styles/js/fontawesome-all.min.js
adam/static/styles/js/jquery-1.8.2.min.js
adam/static/styles/js/jquery-1.8.2.min.js~~Chris_dev
adam/static/styles/js/jquery-1.8.2.min.js~~HEAD
mapsadam-0.2.21.dist-info/DESCRIPTION.rst
mapsadam-0.2.21.dist-info/METADATA
mapsadam-0.2.21.dist-info/RECORD
mapsadam-0.2.21.dist-info/WHEEL
mapsadam-0.2.21.dist-info/metadata.json
mapsadam-0.2.21.dist-info/top_level.txt
